hltex/__init__.py
hltex/cli.py
hltex/context.py
hltex/errors.py
hltex/indentation.py
hltex/pybox.py
hltex/state.py
hltex/translator.py
hltex/control/__init__.py
hltex/control/control.py
hltex/control/eq.py
hltex/control/pysplice.py
hltex-0.0.5.dist-info/DESCRIPTION.rst
hltex-0.0.5.dist-info/METADATA
hltex-0.0.5.dist-info/RECORD
hltex-0.0.5.dist-info/WHEEL
hltex-0.0.5.dist-info/entry_points.txt
hltex-0.0.5.dist-info/metadata.json
hltex-0.0.5.dist-info/top_level.txt
