Metadata-Version: 2.0
Name: hltex
Version: 0.0.5
Summary: A compiler for HLTeX, a higher-level language on top of LaTeX
Home-page: https://github.com/agajews/hltex
Author: Alex Gajewski & Wanqi Zhu
Author-email: agajews@gmail.com
License: UNKNOWN
Platform: UNKNOWN
Classifier: Programming Language :: Python :: 3
Classifier: License :: OSI Approved :: MIT License
Classifier: Operating System :: OS Independent
Requires-Dist: hlbox
